{"stats":{"minecraft:used":{"minecraft:deepslate_bricks":62,"minecraft:coal_block":255},"minecraft:custom":{"minecraft:jump":77,"minecraft:time_since_rest":21133,"minecraft:leave_game":1,"minecraft:damage_dealt":78,"minecraft:walk_on_water_one_cm":6206,"minecraft:sprint_one_cm":8910,"minecraft:play_time":21133,"minecraft:damage_taken":20,"minecraft:time_since_death":21133,"minecraft:walk_one_cm":7996,"minecraft:sneak_time":22,"minecraft:total_world_time":21133,"minecraft:walk_under_water_one_cm":2890,"minecraft:fall_one_cm":2425,"minecraft:fly_one_cm":137210},"minecraft:picked_up":{"minecraft:arrow":1,"minecraft:bone":1}},"DataVersion":3465}